online_store/__init__.py
online_store/__main__.py
online_store/order_management.py
online_store/user_management.py
joke_online_store-0.1.0.dist-info/METADATA
joke_online_store-0.1.0.dist-info/WHEEL
joke_online_store-0.1.0.dist-info/top_level.txt
joke_online_store-0.1.0.dist-info/RECORD
