Metadata-Version: 2.1
Name: joke_online-store
Version: 0.1.0
Summary: Исполняемый пакет для управления пользователями и заказами в онлайн-магазине
Author-email: Pablo_3_16 <p.ergle@edu.centraluniversity.ru>
License: MIT
Requires-Python: >=3.8
Requires-Dist: requests>=2.25.1
Requires-Dist: numpy>=1.19.2
